tutti_aisthetics/__init__.py
tutti_aisthetics/data_generator.py
tutti_aisthetics/keras_utils.py
tutti_aisthetics/losses.py
tutti_aisthetics/nima.py
tutti_aisthetics/scoring.py
tutti_aisthetics/utils.py
tutti_aisthetics/images/__init__.py
tutti_aisthetics/model/__init__.py
tutti_aisthetics/model/weights_aisthetics.hdf5
tutti_aisthetics-3.0.0.dist-info/LICENSE
tutti_aisthetics-3.0.0.dist-info/METADATA
tutti_aisthetics-3.0.0.dist-info/WHEEL
tutti_aisthetics-3.0.0.dist-info/top_level.txt
tutti_aisthetics-3.0.0.dist-info/zip-safe
tutti_aisthetics-3.0.0.dist-info/RECORD
