Metadata-Version: 2.1
Name: tutti-aisthetics
Version: 3.0.0
Summary: A tutti.ch image asthetics AI scorer.
Home-page: UNKNOWN
Author: Oscar Saleta
Author-email: oscar@tutti.ch
License: Proprietary
Keywords: nima,CNN,neural net,MobileNet,aesthetics
Platform: UNKNOWN
Classifier: Programming Language :: Python :: 3
Classifier: Operating System :: OS Independent
Requires-Python: >=3.5.2
Requires-Dist: importlib-resources (>=1.0.2)
Requires-Dist: numpy (>=1.17.0)
Requires-Dist: pillow (>=6.1.0)
Requires-Dist: scikit-learn (>=0.21.0)
Requires-Dist: setuptools (>=41.0.0)
Requires-Dist: tensorflow (>=1.14.0)
